dbt/adapters/openlineage_bigquery/__init__.py
dbt/adapters/openlineage_bigquery/connections.py
dbt/adapters/openlineage_bigquery/impl.py
dbt/adapters/openlineage_bigquery/schema/__init__.py
dbt/include/openlineage_bigquery/__init__.py
dbt/include/openlineage_bigquery/dbt_project.yml
dbt/include/openlineage_bigquery/macros/adapters.sql
dbt/include/openlineage_bigquery/macros/catalog.sql
dbt/include/openlineage_bigquery/macros/etc.sql
marquez_dbt_bigquery-0.16.1.dist-info/METADATA
marquez_dbt_bigquery-0.16.1.dist-info/WHEEL
marquez_dbt_bigquery-0.16.1.dist-info/top_level.txt
marquez_dbt_bigquery-0.16.1.dist-info/RECORD
