Metadata-Version: 2.1
Name: marquez-dbt-bigquery
Version: 0.16.1
Summary: The Marquez BigQuery adapter plugin for dbt (data build tool)
Home-page: UNKNOWN
Author: Marquez Project
License: UNKNOWN
Keywords: marquez
Platform: UNKNOWN
Requires-Python: >=3.6
Requires-Dist: dbt-core (>=0.20.0b1)
Requires-Dist: dbt-bigquery (>=0.20.0b1)
Requires-Dist: sqlparse (>=0.3.1)
Requires-Dist: marquez-integration-common (==0.16.1)
Requires-Dist: openlineage-python (==0.0.1rc6)
Provides-Extra: dev
Requires-Dist: pytest-cov ; extra == 'dev'
Requires-Dist: mock ; extra == 'dev'
Requires-Dist: pytest ; extra == 'dev'
Requires-Dist: flake8 ; extra == 'dev'
Provides-Extra: tests
Requires-Dist: pytest ; extra == 'tests'
Requires-Dist: pytest-cov ; extra == 'tests'
Requires-Dist: mock ; extra == 'tests'
Requires-Dist: flake8 ; extra == 'tests'
